{
  "timestamp": "2026-01-09T00:00:24.107Z",
  "budget": {
    "status": "pass",
    "violations": 0,
    "criticalViolations": 0,
    "recommendations": [
      "Reduce Time to Interactive by minimizing main thread blocking JavaScript"
    ]
  },
  "regression": {
    "totalTests": 4,
    "passRate": 0,
    "averageDeviation": 192.99540121548372,
    "regressionDetected": true
  },
  "recommendations": [
    "Reduce Time to Interactive by minimizing main thread blocking JavaScript",
    "Performance regression detected - investigate recent changes"
  ]
}
